{
  "cacheBootResources": true,
  "config": [ ],
  "debugBuild": false,
  "entryAssembly": "Automachine",
  "icuDataMode": 2,
  "linkerEnabled": true,
  "resources": {
    "assembly": {
      "Automachine.dll": "sha256-3TbZFoDYqxyAMwr2CnEuKes2bCWcIsfcRT9MRUyUD8I=",
      "Microsoft.AspNetCore.Components.dll": "sha256-TCK6KMeI3jqdO19737gydPnyS+M8eH5s96\/CKhRlo6M=",
      "Microsoft.AspNetCore.Components.Web.dll": "sha256-urtEeY4DoG8BjuRiZZA5q6CVWALvWlMdGHye5aQL73w=",
      "Microsoft.AspNetCore.Components.WebAssembly.dll": "sha256-VfuhQtMrvCmEflZYOOSPlstWKSnWBKH\/9leuaVp3ChE=",
      "Microsoft.Extensions.Configuration.Abstractions.dll": "sha256-X\/f4fDl2cuIRXeWHhK\/f2UqQbFioD+RU4a4CEh0zrrQ=",
      "Microsoft.Extensions.Configuration.dll": "sha256-DBOKSPriP2JDxVbbWrLXyD3K4\/x3RBifNBWk\/q1I39M=",
      "Microsoft.Extensions.Configuration.Json.dll": "sha256-nTqLKuydttqLtE3VT3p6XhPmLxuaJDd0cL3Qzt8D4Ro=",
      "Microsoft.Extensions.DependencyInjection.Abstractions.dll": "sha256-tkdkrAT4n35\/Yaa5YMYJpqdzzpHol9Ox3jP0FAYcFPE=",
      "Microsoft.Extensions.DependencyInjection.dll": "sha256-qi0kE7rp0kdsNqdL6DyPZEeimjUGvcLT4iWQX0YnRus=",
      "Microsoft.Extensions.Logging.Abstractions.dll": "sha256-x+N2sgSEct\/XXqose+TJ\/\/8DQXHbcSLTTD03Y22EXT8=",
      "Microsoft.Extensions.Logging.dll": "sha256-oEPPw1EPpaOHv+EHwoT2WcgDiRbjEXxigiW7V44cIYE=",
      "Microsoft.Extensions.Options.dll": "sha256-0fhMx2H0cf76DtazR5+OlRbIi1+vI3PjUYGaW5uG30c=",
      "Microsoft.Extensions.Primitives.dll": "sha256-eXvGx2jcjpTPEJoAHBsW\/VuMPbNyyU+AsuhPmkzSSRY=",
      "Microsoft.JSInterop.dll": "sha256-kJMWds9eiUUJfD84G0n0dDlrOQk6JWHEIUBgZMRYhFY=",
      "Microsoft.JSInterop.WebAssembly.dll": "sha256-gAM0U1w98ffRNyjMybCtgJeQFGgmxqc7CH1\/UxP2p2o=",
      "System.Collections.Concurrent.dll": "sha256-TB8a9DDH1BlGrdHUHFmMGIQR5dUeFAC3pVVzX+Oaca8=",
      "System.Collections.dll": "sha256-b28nHPO\/KNtdvzmN49M\/DmFiG1JUzQldgzuYjE5MPxU=",
      "System.ComponentModel.dll": "sha256-LQCRN10G7vx1ozdhuBeT72jLHw4bNOuR9B5zS7yx1mI=",
      "System.Linq.dll": "sha256-MvlcVptYEM4pbMCWj8W6iSirnKmp4NtltkbbHS2nCKA=",
      "System.Memory.dll": "sha256-LhiI20vyUzSAGjy2\/hiMrS1kcBvV8BG2dFRk+3V68tw=",
      "System.Net.Http.dll": "sha256-mYTg2Z0lOCNNVyiBNZ+0kYKGjN\/cy56rCCMJvEkfGpo=",
      "System.Net.Primitives.dll": "sha256-4JCAtW2+TZj+9sB4EZpr7wDIF75g8WH7W36hs4G4mp4=",
      "System.Private.CoreLib.dll": "sha256-PooxKlL95lHc\/ttajCcBZcQ85XIKg2HkFRsP+3CM3hE=",
      "System.Private.Uri.dll": "sha256-6lR0k3G4pQCC85Yjj\/oCfxgVo4gti8oKRPttOw+YdR4=",
      "System.Runtime.dll": "sha256-y1MoJ9NdDsP40xuI3hD+SS5W\/qwzF6\/Y1yu5P+IoAK0=",
      "System.Runtime.InteropServices.JavaScript.dll": "sha256-u\/PnuRpQ25cPzm2qvQ6r2sFIUMlEl\/CsUks8m2riQHg=",
      "System.Text.Encodings.Web.dll": "sha256-NXJcycwPkccUFCNu0n2sxP9gtjPyjOXALuj6i9hcekw=",
      "System.Text.Json.dll": "sha256-fEDr2La2g24TFY0NqWL2F6vKAXN05tJhPtzzCdEUXd4=",
      "System.Threading.dll": "sha256-bsU+q53OkgajbgMUeEpBf\/m7TEMgC48wljQG6wO4TMs="
    },
    "extensions": null,
    "lazyAssembly": null,
    "libraryInitializers": null,
    "pdb": null,
    "runtime": {
      "dotnet.7.0.1.3rogqc3447.js": "sha256-jjax3FMRXzFAziWowdtJf6vipP2xXAaA5gD6VBYB6Y0=",
      "dotnet.wasm": "sha256-Oxa1EqglhbokFBgIlQ\/Lf4Btg4+I+RdxbMV39OEOUxE="
    },
    "runtimeAssets": {
      "dotnet.wasm": {
        "behavior": "dotnetwasm",
        "hash": "sha256-Oxa1EqglhbokFBgIlQ\/Lf4Btg4+I+RdxbMV39OEOUxE="
      }
    },
    "satelliteResources": null
  }
}